mark_json/__init__.py
mark_json/main.py
mark_json-0.1.1.dist-info/LICENSE
mark_json-0.1.1.dist-info/METADATA
mark_json-0.1.1.dist-info/WHEEL
mark_json-0.1.1.dist-info/top_level.txt
mark_json-0.1.1.dist-info/RECORD
