Metadata-Version: 2.1
Name: mark_json
Version: 0.1.1
Summary: Converts Markdown to a structured JSON format, ideal for long documents
Home-page: https://github.com/marcmarine/mark-json
Author: Marc Mariné
Author-email: shenobi@gmail.com
License: LICENSE
Keywords: markdown md json parser syntax tree
License-File: LICENSE
Requires-Dist: PyYAML==6.0.2
